tctl/__init__.py
tctl/config.py
tctl/credentials.py
tctl/env.py
tctl/inputs.py
tctl/remote.py
tctl/terminal.py
tctl/upgrade.py
tctl/utils.py
tctl/version.py
tctl/connections/__init__.py
tctl/connections/crud.py
tctl/instances/__init__.py
tctl/instances/crud.py
tctl/me/__init__.py
tctl/me/crud.py
tctl/monitors/__init__.py
tctl/monitors/crud.py
tctl/orders/__init__.py
tctl/orders/crud.py
tctl/positions/__init__.py
tctl/positions/crud.py
tctl/pricing/__init__.py
tctl/pricing/price_crud.py
tctl/pricing/rates_crud.py
tctl/sandbox/__init__.py
tctl/sandbox/crud.py
tctl/strategies/__init__.py
tctl/strategies/crud.py
tctl/strategies/crud_versions.py
tctl/tokens/__init__.py
tctl/tokens/crud.py
tctl/tradehooks/__init__.py
tctl/tradehooks/crud.py
tctl/trades/__init__.py
tctl/trades/crud.py
tctl/universe/__init__.py
tctl/universe/assets_crud.py
tctl/universe/brokers_crud.py
tctl/universe/exchanges_crud.py
tctl/volumes/__init__.py
tctl/volumes/crud.py
tctl-0.0.46.dist-info/LICENSE.txt
tctl-0.0.46.dist-info/METADATA
tctl-0.0.46.dist-info/WHEEL
tctl-0.0.46.dist-info/entry_points.txt
tctl-0.0.46.dist-info/top_level.txt
tctl-0.0.46.dist-info/RECORD
