Metadata-Version: 2.1
Name: tctl
Version: 0.0.46
Summary: Tradologics Command-line Utility
Home-page: https://tradologics.com/tctl
Author: Tradologics, Inc.
Author-email: opensource@tradologics.com
License: Apache 2.0
Keywords: tradologics,tradologics.com
Platform: any
Classifier: License :: OSI Approved :: Apache Software License
Classifier: Development Status :: 4 - Beta
Classifier: Operating System :: OS Independent
Classifier: Intended Audience :: Developers
Classifier: Topic :: Office/Business :: Financial
Classifier: Topic :: Office/Business :: Financial :: Investment
Classifier: Topic :: Software Development :: Libraries
Classifier: Topic :: Software Development :: Libraries :: Python Modules
Classifier: Programming Language :: Python :: 3.6
Classifier: Programming Language :: Python :: 3.7
Classifier: Programming Language :: Python :: 3.8
Classifier: Programming Language :: Python :: 3.9
License-File: LICENSE.txt
Requires-Dist: click (>=7.0.0)
Requires-Dist: requests (>=2.24.0)
Requires-Dist: tabulate (>=0.8.0)
Requires-Dist: python-dotenv (>=0.14.0)
Requires-Dist: stdiomask (>=0.0.5)
Requires-Dist: pygments (>=2.6.0)
Requires-Dist: inquirer (>=2.7.0)
Requires-Dist: quantstats (>=0.0.25)
Requires-Dist: PyYAML (>=5.0.0)
Requires-Dist: ujson (>=3.0.0)
Requires-Dist: pandas (>=1.0.0)
Requires-Dist: analytics-python (>=1.2.5)
